flask_notion_database/__init__.py
flask_notion_database/extension.py
flask_notion_database/routes/__init__.py
flask_notion_database/routes/block.py
flask_notion_database/routes/database.py
flask_notion_database/routes/page.py
flask_notion_database-0.0.1.dist-info/LICENSE
flask_notion_database-0.0.1.dist-info/METADATA
flask_notion_database-0.0.1.dist-info/WHEEL
flask_notion_database-0.0.1.dist-info/top_level.txt
flask_notion_database-0.0.1.dist-info/RECORD
