Metadata-Version: 2.1
Name: flask-notion-database
Version: 0.0.1
Summary: notion-database flask extension
Author-email: minwook-shin <minwook0106@gmail.com>
Project-URL: Homepage, https://github.com/minwook-shin/flask-notion-database
Project-URL: Bug Tracker, https://github.com/minwook-shin/flask-notion-database/issues
Classifier: Programming Language :: Python :: 3
Classifier: License :: OSI Approved :: GNU Lesser General Public License v3 (LGPLv3)
Classifier: Operating System :: OS Independent
Classifier: Framework :: Flask
Requires-Python: >=3.9
License-File: LICENSE
Requires-Dist: notion-database==2.0.dev0
Requires-Dist: flask==3.1.0
Provides-Extra: dev
Requires-Dist: flasgger; extra == "dev"
Requires-Dist: build; extra == "dev"
Requires-Dist: twine; extra == "dev"
